{
	"autorun": true,
	"terminals": [
		{
			"name": "project-terminal",
			"focus": true,
			"execute": false,
			"command": "npm start"
		},
		{
			"name": "project-terminal-eslint",
			"focus": true,
			"execute": false,
			"command": ""
		},
		{
			"name": "project-terminal-prettier",
			"focus": true,
			"execute": false,
			"command": ""
		},
		{
			"name": "project-terminal-ts",
			"focus": true,
			"execute": false,
			"command": ""
		},
    {
			"name": "misc",
			"open": true,
      "command": ""
		}
	]
}
